projects/pattern_detector/design/pattern_detector1.v
module pattern_detector1(
    input IN,
    input clock,
    output OUT
);
	reg Qa, Qb, IN;
    
    always @(posedge clock)
        case({Qa,Qb,IN})
		3'b000: begin 
			{Qa,Qb} <= 2'b00;
			assign OUT = 0;
		end
		3'b001: begin
			{Qa,Qb} <= 2'b01;
			assign OUT = 0;
		end
		3'b010: begin
			{Qa,Qb} <= 2'b00;
			assign OUT = 0;
		end
		3'b011: begin 
			{Qa,Qb} <= 2'b10;
			assign OUT = 0;
		end
		3'b100: begin
			{Qa,Qb} <= 2'b00;
			assign OUT = 0;
		end
		3'b101: begin
			{Qa,Qb} <= 2'b11;
			assign OUT = 1;
		end
		3'b110: begin 
			{Qa,Qb} <= 2'b00;
			assign OUT = 0;
		end
		3'b111: begin
			{Qa,Qb} <= 2'b11;
			assign OUT = 1;
		end
	endcase
endmodule

projects/pattern_detector/testbench/pattern_detector1tb.v
module pattern_detector1tb();
    reg IN;
    reg clock;
    wire OUT;
    
    pattern_detector1 dut(
        .IN(IN),
        .clock(clock),
        .OUT(OUT)
    );
    
    always #5 clock = ~clock; 
    
    initial begin
        $dumpfile("pattern_detector1.vcd");
        $dumpvars(0, pattern_detector1tb);
        clock = 0;
        IN = 0;
        #10 IN = 1; 
        #10 IN = 0; 
        #10 IN = 1; 
        #10 IN = 1; 
        #10 IN = 0; 
        #10 IN = 1; 
        #10 IN = 1; 
        #10 IN = 0;
        #10 IN = 0;
        #10 IN = 1;
        #10 IN = 1;
        #10 IN = 1;
        #10 IN = 1;
        #10 IN = 1;
        #10 IN = 0;
        #10 IN = 1;
        #10 IN = 1;
        #10 IN = 1;
        #10 IN = 1;
        #10 IN = 0;
        #10 IN = 1;
        #20;
        $finish;
    end
    initial begin
        $monitor("Time = %0t, IN = %b, OUT = %b", $time, IN, OUT);
    end
endmodule

projects/pattern_detector/results/waveforms/pattern_detector1.vcd
$date
   Sun Mar  9 11:16:34 2025
$end

$version
  2024.2.0
  $dumpfile ("pattern_detector1.vcd") 
$end

$timescale
  1ps
$end

$scope module pattern_detector1tb $end
$var reg 1 ! IN $end
$var reg 1 " clock $end
$var wire 1 # OUT $end
$scope module dut $end
$var wire 1 $ IN $end
$var wire 1 % clock $end
$var reg 1 & OUT $end
$var reg 1 ' Qa $end
$var reg 1 ( Qb $end
$upscope $end
$upscope $end
$enddefinitions $end

#0
$dumpvars
0!
0"
x#
0$
0%
x&
x'
x(
$end

#5000
1"
0#
1%
0&
0'
0(

#10000
1!
0"
1$
0%

#15000
1"
1%
1(

#20000
0!
0"
0$
0%

#25000
1"
1%
0(

#30000
1!
0"
1$
0%

#35000
1"
1%
1(

#40000
0"
0%

#45000
1"
1%
1'
0(

#50000
0!
0"
0$
0%

#55000
1"
1%
0'

#60000
1!
0"
1$
0%

#65000
1"
1%
1(

#70000
0"
0%

#75000
1"
1%
1'
0(

#80000
0!
0"
0$
0%

#85000
1"
1%
0'

#90000
0"
0%

#95000
1"
1%

#100000
1!
0"
1$
0%

#105000
1"
1%
1(

#110000
0"
0%

#115000
1"
1%
1'
0(

#120000
0"
0%

#125000
1"
1#
1%
1&
1(

#130000
0"
0%

#135000
1"
1%

#140000
0"
0%

#145000
1"
1%

#150000
0!
0"
0$
0%

#155000
1"
0#
1%
0&
0'
0(

#160000
1!
0"
1$
0%

#165000
1"
1%
1(

#170000
0"
0%

#175000
1"
1%
1'
0(

#180000
0"
0%

#185000
1"
1#
1%
1&
1(

#190000
0"
0%

#195000
1"
1%

#200000
0!
0"
0$
0%

#205000
1"
0#
1%
0&
0'
0(

#210000
1!
0"
1$
0%

#215000
1"
1%
1(

