projects/digital_clock/design/digital_clock.v
module digital_clock(
    input clock,        
    input reset,        
    output reg [5:0] sec,
    output reg [5:0] min,
    output reg [4:0] hour
);

    reg [31:0] counter;

    always @(posedge clock or posedge reset) begin
        if (reset) begin
            sec <= 0;
            min <= 0;
            hour <= 0;
            counter <= 0;
        end else begin
            counter <= counter + 1;
            
            // Assuming the system clock is 50 MHz, we need 50,000,000 cycles for 1 second
            if (counter == 50_000_000) begin
                counter <= 0;
                sec <= sec + 1;

                if (sec == 59) begin
                    sec <= 0;
                    min <= min + 1;

                    if (min == 59) begin
                        min <= 0;
                        hour <= hour + 1;

                        if (hour == 23) begin
                            hour <= 0;
                        end
                    end
                end
            end
        end
    end
endmodule

projects/digital_clock/testbench/clock_tb.v
`timescale 1ns/1ps

module clock_tb;
    reg clock, reset;
    wire [5:0] sec, min;
    wire [4:0] hour;

    digital_clock uut (
        .clock(clock),
        .reset(reset),
        .sec(sec),
        .min(min),
        .hour(hour)
    );

    // Generate a 50 MHz clock
    always #1 clock = ~clock;  // Toggle clock every 1 ns 

    initial begin
        $dumpfile("clock_waveform.vcd");
        $dumpvars(0, clock_tb);

        clock = 0;
        reset = 1;
        #5 reset = 0; // Release reset after 50 ns
        #1_000_000_000; // Run simulation for 1 second

        $finish;
    end
endmodule

projects/digital_clock/results/waveforms/clock_waveform.vcd
$date
   Sun Mar  9 15:12:51 2025
$end

$version
  2024.2.0
  $dumpfile ("clock_waveform.vcd") 
$end

$timescale
  1ps
$end

$scope module clock_tb $end
$var reg 1 ! clock $end
$var reg 1 " reset $end
$var wire 6 # sec [5:0] $end
$var wire 6 $ min [5:0] $end
$var wire 5 % hour [4:0] $end
$scope module uut $end
$var wire 1 & clock $end
$var wire 1 ' reset $end
$var reg 6 ( sec [5:0] $end
$var reg 6 ) min [5:0] $end
$var reg 5 * hour [4:0] $end
$var reg 32 + counter [31:0] $end
$upscope $end
$upscope $end
$enddefinitions $end

#0
$dumpvars
0!
1"
b0 #
b0 $
b0 %
0&
1'
b0 (
b0 )
b0 *
b0 +
$end

#1000
1!
1&

#2000
0!
0&

#3000
1!
1&

#4000
0!
0&

#5000
1!
0"
1&
0'
b1 +

#6000
0!
0&

#7000
1!
b1 #
1&
b1 (
b0 +

#8000
0!
0&

#9000
1!
1&
b1 +

#10000
0!
0&

#11000
1!
b10 #
1&
b10 (
b0 +

#12000
0!
0&

#13000
1!
1&
b1 +

#14000
0!
0&

#15000
1!
b11 #
1&
b11 (
b0 +

#16000
0!
0&

#17000
1!
1&
b1 +

#18000
0!
0&

#19000
1!
b100 #
1&
b100 (
b0 +

#20000
0!
0&

#21000
1!
1&
b1 +

#22000
0!
0&

#23000
1!
b101 #
1&
b101 (
b0 +

#24000
0!
0&

#25000
1!
1&
b1 +

#26000
0!
0&

#27000
1!
b110 #
1&
b110 (
b0 +

#28000
0!
0&

#29000
1!
1&
b1 +

#30000
0!
0&

#31000
1!
b111 #
1&
b111 (
b0 +

#32000
0!
0&

#33000
1!
1&
b1 +

#34000
0!
0&

#35000
1!
b1000 #
1&
b1000 (
b0 +

#36000
0!
0&

#37000
1!
1&
b1 +

#38000
0!
0&

#39000
1!
b1001 #
1&
b1001 (
b0 +

#40000
0!
0&

#41000
1!
1&
b1 +

#42000
0!
0&

#43000
1!
b1010 #
1&
b1010 (
b0 +

#44000
0!
0&

#45000
1!
1&
b1 +

#46000
0!
0&

#47000
1!
b1011 #
1&
b1011 (
b0 +

#48000
0!
0&

#49000
1!
1&
b1 +

#50000
0!
0&

#51000
1!
b1100 #
1&
b1100 (
b0 +

#52000
0!
0&

#53000
1!
1&
b1 +

#54000
0!
0&

#55000
1!
b1101 #
1&
b1101 (
b0 +

#56000
0!
0&

#57000
1!
1&
b1 +

#58000
0!
0&

#59000
1!
b1110 #
1&
b1110 (
b0 +

#60000
0!
0&

#61000
1!
1&
b1 +

#62000
0!
0&

#63000
1!
b1111 #
1&
b1111 (
b0 +

#64000
0!
0&

#65000
1!
1&
b1 +

#66000
0!
0&

#67000
1!
b10000 #
1&
b10000 (
b0 +

#68000
0!
0&

#69000
1!
1&
b1 +

#70000
0!
0&

#71000
1!
b10001 #
1&
b10001 (
b0 +

#72000
0!
0&

#73000
1!
1&
b1 +

#74000
0!
0&

#75000
1!
b10010 #
1&
b10010 (
b0 +

#76000
0!
0&

#77000
1!
1&
b1 +

#78000
0!
0&

#79000
1!
b10011 #
1&
b10011 (
b0 +

#80000
0!
0&

#81000
1!
1&
b1 +

#82000
0!
0&

#83000
1!
b10100 #
1&
b10100 (
b0 +

#84000
0!
0&

#85000
1!
1&
b1 +

#86000
0!
0&

#87000
1!
b10101 #
1&
b10101 (
b0 +

#88000
0!
0&

#89000
1!
1&
b1 +

#90000
0!
0&

#91000
1!
b10110 #
1&
b10110 (
b0 +

#92000
0!
0&

#93000
1!
1&
b1 +

#94000
0!
0&

#95000
1!
b10111 #
1&
b10111 (
b0 +

#96000
0!
0&

#97000
1!
1&
b1 +

#98000
0!
0&

#99000
1!
b11000 #
1&
b11000 (
b0 +

